mathexpand/__init__.py
mathexpand/digits.py
mathexpand-1.3.0.dist-info/LICENSE
mathexpand-1.3.0.dist-info/METADATA
mathexpand-1.3.0.dist-info/WHEEL
mathexpand-1.3.0.dist-info/top_level.txt
mathexpand-1.3.0.dist-info/RECORD
