Metadata-Version: 2.1
Name: mathexpand
Version: 1.3.0
Summary: A math expand package
Home-page: https://github.com/gi-b716/math-expand
Author: GavinCQTD
Author-email: gavingan2012@gmail.com
Classifier: Programming Language :: Python :: 3
Classifier: License :: OSI Approved :: MIT License
Classifier: Operating System :: OS Independent
Requires-Python: >=3.0
License-File: LICENSE
